aquarium/__init__.py
aquarium/aquarium.py
aquarium/auth.py
aquarium/edge.py
aquarium/element.py
aquarium/entity.py
aquarium/events.py
aquarium/exceptions.py
aquarium/item.py
aquarium/tools.py
aquarium/utils.py
aquarium/items/__init__.py
aquarium/items/asset.py
aquarium/items/bot.py
aquarium/items/organisation.py
aquarium/items/playlist.py
aquarium/items/project.py
aquarium/items/shot.py
aquarium/items/task.py
aquarium/items/template.py
aquarium/items/user.py
aquarium/items/usergroup.py
aquarium_python_api-2.2.0.dist-info/licenses/LICENSE.md
aquarium_python_api-2.2.0.dist-info/METADATA
aquarium_python_api-2.2.0.dist-info/WHEEL
aquarium_python_api-2.2.0.dist-info/top_level.txt
aquarium_python_api-2.2.0.dist-info/RECORD
