Metadata-Version: 2.4
Name: aquarium-python-api
Version: 2.2.0
Summary: Aquarium python package
Home-page: https://docs.python.aquarium.app
Author: Fatfish Lab
Author-email: lab@fatfi.sh
License: gpl-3.0
Project-URL: Documentation, https://docs.python.aquarium.app
Project-URL: Source, https://github.com/fatfish-lab/aquarium-python-api
Project-URL: Aquarium, https://fatfi.sh/aquarium
Keywords: fatfish,lab,fatfishlab,aquarium,studio,project,management,nodal,sdk,rest,cgi,vfx,api,python
Platform: any
Classifier: Development Status :: 5 - Production/Stable
Classifier: Intended Audience :: Developers
Classifier: Operating System :: OS Independent
Classifier: Programming Language :: Python :: 2
Classifier: Programming Language :: Python :: 3
Classifier: License :: OSI Approved :: GNU General Public License v3 (GPLv3)
License-File: LICENSE.md
Requires-Dist: requests>=2.25.1
Requires-Dist: dotmap==1.3.23
Requires-Dist: pytz>=2020.5
Provides-Extra: dev
Requires-Dist: sphinx>=3.4.3; extra == "dev"
Requires-Dist: furo>=0.5.1; extra == "dev"
Requires-Dist: sphinx-copybutton>=0.3.1; extra == "dev"
Requires-Dist: myst-parser>=0.13.3; extra == "dev"
Dynamic: license-file
